[
{
    "code": "TD",
    "name": "Chad"
},
{
    "code": "CL",
    "name": "Chile"
},
{
    "code": "CN",
    "name": "China"
},
{
    "code": "CX",
    "name": "Christmas Island"
},
{
    "code": "CZ",
    "name": "Czech Republic"
},
{
    "code": "GF",
    "name": "French Guiana"
},
{
    "code": "PF",
    "name": "French Polynesia"
},
{
    "code": "TF",
    "name": "French Southern Territories"
},
{
    "code": "LI",
    "name": "Liechtenstein"
},
{
    "code": "MF",
    "name": "Saint Martin (French part)"
},
{
    "code": "SC",
    "name": "Seychelles"
},
{
    "code": "SX",
    "name": "Sint Maarten (Dutch part)"
},
{
    "code": "GS",
    "name": "South Georgia and the South Sandwich Islands"
},
{
    "code": "TW",
    "name": "Taiwan, Province of China"
}
]